kw3/__init__.py
kw3/kweb3.py
kw3-0.0.24.dist-info/LICENSE
kw3-0.0.24.dist-info/METADATA
kw3-0.0.24.dist-info/WHEEL
kw3-0.0.24.dist-info/top_level.txt
kw3-0.0.24.dist-info/RECORD
